api_config_menu.py
chat_menu.py
cli.py
conversation_history.py
main.py
agent/__init__.py
agent/agent.py
model_manager/__init__.py
model_manager/azure_adapter.py
model_manager/gemini_adapter.py
model_manager/model_manager.py
model_manager/openai_adapter.py
model_manager/openrouter_adapter.py
prompt_manager/__init__.py
prompt_manager/prompts.py
tool/__init__.py
tool/ast_grep.py
tool/block_edit.py
tool/create.py
tool/delete.py
tool/directory_utils.py
tool/edit.py
tool/external_terminal.py
tool/external_terminal_runner.py
tool/git_changes.py
tool/grep.py
tool/linting_checker.py
tool/read.py
tool/read_many.py
tool/search_and_read.py
tool/search_index.py
tool/semgrep.py
tool/terminal.py
tool/terminal_guard.py
tool/web_reader.py
tool/web_search.py
tool_spec/__init__.py
tool_spec/lyne_tool_spec.py
util/__init__.py
util/app_dirs.py
util/filesystem_indexer.py
util/logging.py
vcs/__init__.py
vcs/backup_manager.py
vcs/diff_viewer.py
vcs/version_control.py
lynecode-0.3.1.dist-info/METADATA
lynecode-0.3.1.dist-info/WHEEL
lynecode-0.3.1.dist-info/entry_points.txt
lynecode-0.3.1.dist-info/top_level.txt
lynecode-0.3.1.dist-info/RECORD
