Metadata-Version: 2.4
Name: lynecode
Version: 0.3.1
Summary: Lyne: AI CODING ASSISTANT
Author: MD ZAID ANWAR
License-Expression: MIT
Keywords: terminal,ai agent,code,AI Coding tool,coding assistant,ai
Classifier: Development Status :: 4 - Beta
Classifier: Intended Audience :: Developers
Classifier: Operating System :: OS Independent
Classifier: Programming Language :: Python
Classifier: Programming Language :: Python :: 3
Classifier: Programming Language :: Python :: 3.9
Classifier: Programming Language :: Python :: 3.10
Classifier: Programming Language :: Python :: 3.11
Classifier: Programming Language :: Python :: 3.12
Classifier: Topic :: Software Development :: Libraries :: Application Frameworks
Classifier: Topic :: Software Development :: Version Control
Classifier: Environment :: Console
Requires-Python: >=3.9
Requires-Dist: rich<14,>=13
Requires-Dist: openai>=1.40
Requires-Dist: google-genai>=0.5
Requires-Dist: requests>=2.31
Requires-Dist: regex>=2024.5.15
Requires-Dist: aiofiles>=23.2
Requires-Dist: beautifulsoup4>=4.12
Requires-Dist: curl_cffi>=0.6
Requires-Dist: trafilatura>=1.6
Requires-Dist: readability-lxml>=0.8
Requires-Dist: tqdm>=4.66
Requires-Dist: ddgs>=2.6
Requires-Dist: json5>=0.9
Requires-Dist: rapidfuzz>=3.0
Requires-Dist: ast-grep-py==0.39.4
Provides-Extra: dev
Requires-Dist: pylint>=3.0; extra == "dev"
Requires-Dist: cpplint>=1.6; extra == "dev"
Requires-Dist: cppcheck>=2.9; platform_system == "Windows" and extra == "dev"
Requires-Dist: pyjslint>=0.3; extra == "dev"
Requires-Dist: sqlfluff>=3.0; extra == "dev"
Requires-Dist: semgrep>=1.90; extra == "dev"
